{
  "sources": [
    {
      "title": "Bankless Shows",
      "feedUrl": "https://shows.banklesshq.com/feed",
      "siteUrl": "https://shows.banklesshq.com",
      "articles": [
        {
          "id": "https://shows.banklesshq.com/p/debrief-the-pow-vs-pos-debate-lyn-a98",
          "author": "Ryan Sean Adams",
          "description": "Listen now (46 min) | Debriefing the debate with Lyn Alden & Justin Drake.",
          "link": "https://shows.banklesshq.com/p/debrief-the-pow-vs-pos-debate-lyn-a98",
          "publishedOn": "2022-03-28T18:01:40.000Z",
          "wordCount": null,
          "title": "DEBRIEF - The PoW vs. PoS Debate | Lyn Alden & Justin Drake",
          "itunes": {},
          "enclosure": {
            "url": "https://cdn.substack.com/image/youtube/w_728,c_limit/QBIjMCAeqSc",
            "length": "0",
            "type": "image/jpeg"
          },
          "imageUrl": "https://cdn.substack.com/image/youtube/w_728,c_limit/QBIjMCAeqSc"
        },
        {
          "id": "https://shows.banklesshq.com/p/the-pow-vs-pos-debate-lyn-alden-and",
          "author": "Ryan Sean Adams",
          "description": "Which is the future of the global money system?",
          "link": "https://shows.banklesshq.com/p/the-pow-vs-pos-debate-lyn-alden-and",
          "publishedOn": "2022-03-28T10:30:38.000Z",
          "wordCount": null,
          "title": "The PoW vs. PoS Debate | Lyn Alden & Justin Drake",
          "itunes": {},
          "enclosure": {
            "url": "https://bucketeer-e05bbc84-baa3-437e-9518-adb32be77984.s3.amazonaws.com/public/images/fa75ceae-848b-4335-a476-0db49de848d7_2061x1159.jpeg",
            "length": "0",
            "type": "image/jpeg"
          },
          "imageUrl": "https://bucketeer-e05bbc84-baa3-437e-9518-adb32be77984.s3.amazonaws.com/public/images/fa75ceae-848b-4335-a476-0db49de848d7_2061x1159.jpeg"
        },
        {
          "id": "https://shows.banklesshq.com/p/shibuyas-rethinking-production-studios",
          "author": "David Hoffman",
          "description": "Listen now (53 min) | Web3 storytelling at its best",
          "link": "https://shows.banklesshq.com/p/shibuyas-rethinking-production-studios",
          "publishedOn": "2022-03-27T18:08:59.000Z",
          "wordCount": null,
          "title": "Shibuya’s Rethinking Production Studios with pplpleasr, Maciej Kuciara & Jacky | Alpha Leak",
          "itunes": {},
          "enclosure": {
            "url": "https://cdn.substack.com/image/youtube/w_728,c_limit/UgYAPkc29-A",
            "length": "0",
            "type": "image/jpeg"
          },
          "imageUrl": "https://cdn.substack.com/image/youtube/w_728,c_limit/UgYAPkc29-A"
        },
        {
          "id": "https://shows.banklesshq.com/p/early-access-the-proof-of-work-vs",
          "author": "Ryan Sean Adams",
          "description": "Listen now (89 min) | Which is the future of the global money system?",
          "link": "https://shows.banklesshq.com/p/early-access-the-proof-of-work-vs",
          "publishedOn": "2022-03-26T11:58:25.000Z",
          "wordCount": null,
          "title": "EARLY ACCESS: PoW vs PoS | Lyn Alden & Justin Drake",
          "itunes": {},
          "enclosure": {
            "url": "https://cdn.substack.com/image/youtube/w_728,c_limit/1m12zgJ42dI",
            "length": "0",
            "type": "image/jpeg"
          },
          "imageUrl": "https://cdn.substack.com/image/youtube/w_728,c_limit/1m12zgJ42dI"
        },
        {
          "id": "https://shows.banklesshq.com/p/rollup-the-institutions-are-here",
          "author": "Ryan Sean Adams",
          "description": "Listen now (101 min) | 4th Week of March 2022",
          "link": "https://shows.banklesshq.com/p/rollup-the-institutions-are-here",
          "publishedOn": "2022-03-25T10:47:16.000Z",
          "wordCount": null,
          "title": "ROLLUP: The Institutions Are Here | Vitalik & Brady BFFs | Verge of the Merge | Senator Warren, Sup?",
          "itunes": {},
          "enclosure": {
            "url": "https://cdn.substack.com/image/youtube/w_728,c_limit/YPlTLr3u8CU",
            "length": "0",
            "type": "image/jpeg"
          },
          "imageUrl": "https://cdn.substack.com/image/youtube/w_728,c_limit/YPlTLr3u8CU"
        },
        {
          "id": "https://shows.banklesshq.com/p/crypto-in-ukraine-alex-bornyakov",
          "author": "Ryan Sean Adams",
          "description": "Listen now (52 min) | How crypto is making an impact",
          "link": "https://shows.banklesshq.com/p/crypto-in-ukraine-alex-bornyakov",
          "publishedOn": "2022-03-25T01:23:54.000Z",
          "wordCount": null,
          "title": "Crypto in Ukraine | Alex Bornyakov, Deputy Minister of Digital Transformation of Ukraine",
          "itunes": {},
          "enclosure": {
            "url": "https://cdn.substack.com/image/youtube/w_728,c_limit/ezEvnLu6X4w",
            "length": "0",
            "type": "image/jpeg"
          },
          "imageUrl": "https://cdn.substack.com/image/youtube/w_728,c_limit/ezEvnLu6X4w"
        },
        {
          "id": "https://shows.banklesshq.com/p/celestias-building-the-multi-chain",
          "author": "David Hoffman",
          "description": "Listen now (55 min) | All things modular blockchains explained",
          "link": "https://shows.banklesshq.com/p/celestias-building-the-multi-chain",
          "publishedOn": "2022-03-23T11:44:12.000Z",
          "wordCount": null,
          "title": "Celestia’s Building the Multi-Chain Universe with Nick White | Alpha Leak",
          "itunes": {},
          "enclosure": {
            "url": "https://cdn.substack.com/image/youtube/w_728,c_limit/bmSU3cZhe3U",
            "length": "0",
            "type": "image/jpeg"
          },
          "imageUrl": "https://cdn.substack.com/image/youtube/w_728,c_limit/bmSU3cZhe3U"
        },
        {
          "id": "https://shows.banklesshq.com/p/-yuga-labs-buys-out-cryptopunks-bullish",
          "author": "Ryan Sean Adams",
          "description": "Listen now (51 min) | What's the deal with ApeCoin?",
          "link": "https://shows.banklesshq.com/p/-yuga-labs-buys-out-cryptopunks-bullish",
          "publishedOn": "2022-03-23T07:51:26.000Z",
          "wordCount": null,
          "title": "📺 Yuga Labs Buys Out CryptoPunks; Bullish or Bearish for Punks? | Zeneca, Andy8052, Scott Lewis",
          "itunes": {},
          "enclosure": {
            "url": "https://cdn.substack.com/image/youtube/w_728,c_limit/sV7ltCpQs30",
            "length": "0",
            "type": "image/jpeg"
          },
          "imageUrl": "https://cdn.substack.com/image/youtube/w_728,c_limit/sV7ltCpQs30"
        },
        {
          "id": "https://shows.banklesshq.com/p/how-to-become-a-vc-with-haseeb-qureshi",
          "author": "David Hoffman",
          "description": "Listen now (62 min) | The Dynamics of Being a Web3 Venture Capitalist",
          "link": "https://shows.banklesshq.com/p/how-to-become-a-vc-with-haseeb-qureshi",
          "publishedOn": "2022-03-22T08:11:15.000Z",
          "wordCount": null,
          "title": "How to Become a VC with Haseeb Qureshi | Layer Zero",
          "itunes": {},
          "enclosure": {
            "url": "https://cdn.substack.com/image/youtube/w_728,c_limit/SDL6ijF8-JI",
            "length": "0",
            "type": "image/jpeg"
          },
          "imageUrl": "https://cdn.substack.com/image/youtube/w_728,c_limit/SDL6ijF8-JI"
        },
        {
          "id": "https://shows.banklesshq.com/p/debrief-alexis",
          "author": "Ryan Sean Adams",
          "description": "Listen now (21 min) | Debriefing the Episode with Alexis",
          "link": "https://shows.banklesshq.com/p/debrief-alexis",
          "publishedOn": "2022-03-21T10:30:32.000Z",
          "wordCount": null,
          "title": "DEBRIEF - Alexis Ohanian",
          "itunes": {},
          "enclosure": {
            "url": "https://cdn.substack.com/image/youtube/w_728,c_limit/jTxwy1zf2iE",
            "length": "0",
            "type": "image/jpeg"
          },
          "imageUrl": "https://cdn.substack.com/image/youtube/w_728,c_limit/jTxwy1zf2iE"
        },
        {
          "id": "https://shows.banklesshq.com/p/110-alexis",
          "author": "Ryan Sean Adams",
          "description": "How the Reddit Co-Founder Got Crypto-Pilled",
          "link": "https://shows.banklesshq.com/p/110-alexis",
          "publishedOn": "2022-03-21T10:30:32.000Z",
          "wordCount": null,
          "title": "🎙 110 - The Internet Reset | Alexis Ohanian",
          "itunes": {},
          "enclosure": {
            "url": "https://cdn.substack.com/image/youtube/w_728,c_limit/Zimx60Rx8cM",
            "length": "0",
            "type": "image/jpeg"
          },
          "imageUrl": "https://cdn.substack.com/image/youtube/w_728,c_limit/Zimx60Rx8cM"
        },
        {
          "id": "https://shows.banklesshq.com/p/early-access-the-internet-reset-alexis",
          "author": "Ryan Sean Adams",
          "description": "Listen now (61 min) | How the Reddit Co-Founder Got Crypto-Pilled",
          "link": "https://shows.banklesshq.com/p/early-access-the-internet-reset-alexis",
          "publishedOn": "2022-03-18T22:00:37.000Z",
          "wordCount": null,
          "title": "EARLY ACCESS: The Internet Reset | Alexis Ohanian",
          "itunes": {},
          "enclosure": {
            "url": "https://bucketeer-e05bbc84-baa3-437e-9518-adb32be77984.s3.amazonaws.com/public/images/e7e71c89-a975-48fe-9416-9451e683ea05_1280x720.png",
            "length": "0",
            "type": "image/jpeg"
          },
          "imageUrl": "https://bucketeer-e05bbc84-baa3-437e-9518-adb32be77984.s3.amazonaws.com/public/images/e7e71c89-a975-48fe-9416-9451e683ea05_1280x720.png"
        },
        {
          "id": "https://shows.banklesshq.com/p/rollup-eth-merge-soon-yuga-labs-acquisition",
          "author": "Ryan Sean Adams",
          "description": "Listen now (116 min) | 3rd Week of March, 2022",
          "link": "https://shows.banklesshq.com/p/rollup-eth-merge-soon-yuga-labs-acquisition",
          "publishedOn": "2022-03-18T10:56:55.000Z",
          "wordCount": null,
          "title": "ROLLUP: ETH Merge Soon | Yuga Labs Acquisition | ApeCoin | Raises & NEW Releases Galore",
          "itunes": {},
          "enclosure": {
            "url": "https://cdn.substack.com/image/youtube/w_728,c_limit/kxJj9s_6EgE",
            "length": "0",
            "type": "image/jpeg"
          },
          "imageUrl": "https://cdn.substack.com/image/youtube/w_728,c_limit/kxJj9s_6EgE"
        },
        {
          "id": "https://shows.banklesshq.com/p/does-decentralization-matter-kevin",
          "author": "David Hoffman",
          "description": "What new users believe and much more",
          "link": "https://shows.banklesshq.com/p/does-decentralization-matter-kevin",
          "publishedOn": "2022-03-17T10:30:34.000Z",
          "wordCount": null,
          "title": "Does Decentralization Matter? | Kevin Owocki & Cooper Turley",
          "itunes": {},
          "enclosure": {
            "url": "https://cdn.substack.com/image/youtube/w_728,c_limit/PkNPwvaZgTc",
            "length": "0",
            "type": "image/jpeg"
          },
          "imageUrl": "https://cdn.substack.com/image/youtube/w_728,c_limit/PkNPwvaZgTc"
        },
        {
          "id": "https://shows.banklesshq.com/p/bull-or-bear-what-the-charts-are",
          "author": "Ryan Sean Adams",
          "description": "All eyes on what happens next",
          "link": "https://shows.banklesshq.com/p/bull-or-bear-what-the-charts-are",
          "publishedOn": "2022-03-16T10:30:29.000Z",
          "wordCount": null,
          "title": "Bull or Bear? What the Charts Are Saying | Ledger from Up Only",
          "itunes": {},
          "enclosure": {
            "url": "https://cdn.substack.com/image/youtube/w_728,c_limit/ZMv2gRBqaa8",
            "length": "0",
            "type": "image/jpeg"
          },
          "imageUrl": "https://cdn.substack.com/image/youtube/w_728,c_limit/ZMv2gRBqaa8"
        },
        {
          "id": "https://shows.banklesshq.com/p/-tarun-chitra-on-whether-code-is",
          "author": "David Hoffman",
          "description": "Upgrading Global Governance and Exploring the Beauty of Math",
          "link": "https://shows.banklesshq.com/p/-tarun-chitra-on-whether-code-is",
          "publishedOn": "2022-03-15T12:45:31.000Z",
          "wordCount": null,
          "title": "🎙 Tarun Chitra on whether Code is Law | Layer Zero",
          "itunes": {},
          "enclosure": {
            "url": "https://cdn.substack.com/image/youtube/w_728,c_limit/8q8Oxbo_fhw",
            "length": "0",
            "type": "image/jpeg"
          },
          "imageUrl": "https://cdn.substack.com/image/youtube/w_728,c_limit/8q8Oxbo_fhw"
        },
        {
          "id": "https://shows.banklesshq.com/p/-109-sbf-and-the-future-of-ftx-sam",
          "author": "Ryan Sean Adams",
          "description": "Sam Bankman-Fried will make $1 Trillion and Give It Away",
          "link": "https://shows.banklesshq.com/p/-109-sbf-and-the-future-of-ftx-sam",
          "publishedOn": "2022-03-14T10:30:49.000Z",
          "wordCount": null,
          "title": "🎙 109 - SBF and the Future of FTX | Sam Bankman-Fried",
          "itunes": {},
          "enclosure": {
            "url": "https://bucketeer-e05bbc84-baa3-437e-9518-adb32be77984.s3.amazonaws.com/public/images/46baea2b-7177-4b08-b848-9965049b6616_2668x1501.jpeg",
            "length": "0",
            "type": "image/jpeg"
          },
          "imageUrl": "https://bucketeer-e05bbc84-baa3-437e-9518-adb32be77984.s3.amazonaws.com/public/images/46baea2b-7177-4b08-b848-9965049b6616_2668x1501.jpeg"
        },
        {
          "id": "https://shows.banklesshq.com/p/debrief-sbf",
          "author": "Ryan Sean Adams",
          "description": "Listen now (22 min) | Debriefing the Episode with SBF",
          "link": "https://shows.banklesshq.com/p/debrief-sbf",
          "publishedOn": "2022-03-14T10:30:48.000Z",
          "wordCount": null,
          "title": "DEBRIEF - SBF | Sam Bankman-Fried",
          "itunes": {},
          "enclosure": {
            "url": "https://cdn.substack.com/image/youtube/w_728,c_limit/YZ82EdcbnDs",
            "length": "0",
            "type": "image/jpeg"
          },
          "imageUrl": "https://cdn.substack.com/image/youtube/w_728,c_limit/YZ82EdcbnDs"
        },
        {
          "id": "https://shows.banklesshq.com/p/early-access-sbf",
          "author": "Ryan Sean Adams",
          "description": "Listen now (82 min) | Sam Bankman-Fried will make $1 Trillion and Give It Away",
          "link": "https://shows.banklesshq.com/p/early-access-sbf",
          "publishedOn": "2022-03-12T10:30:36.000Z",
          "wordCount": null,
          "title": "EARLY ACCESS: SBF and the Future of FTX",
          "itunes": {},
          "enclosure": {
            "url": "https://cdn.substack.com/image/youtube/w_728,c_limit/pHrhOg4l4Gw",
            "length": "0",
            "type": "image/jpeg"
          },
          "imageUrl": "https://cdn.substack.com/image/youtube/w_728,c_limit/pHrhOg4l4Gw"
        },
        {
          "id": "https://shows.banklesshq.com/p/rollup-bidens-crypto-executive-order",
          "author": "Ryan Sean Adams",
          "description": "2nd Week of March, 2022",
          "link": "https://shows.banklesshq.com/p/rollup-bidens-crypto-executive-order",
          "publishedOn": "2022-03-10T11:30:37.000Z",
          "wordCount": null,
          "title": "ROLLUP: Biden’s Crypto Executive Order | Sanctions & Commodities | Coinbase & MetaMask | Bear Watch?!",
          "itunes": {},
          "enclosure": {
            "url": "https://cdn.substack.com/image/youtube/w_728,c_limit/lslsJp-ykQg",
            "length": "0",
            "type": "image/jpeg"
          },
          "imageUrl": "https://cdn.substack.com/image/youtube/w_728,c_limit/lslsJp-ykQg"
        }
      ]
    }
  ],
  "cliVersion": "1.14.4"
}